Metadata-Version: 2.1
Name: pamogk
Version: 2.2.0
Summary: PAMOGK
Home-page: https://github.com/tastanlab/pamogk
Keywords: pamogk,multi view kernel clustering
Author: Fma
Author-email: fmakdemir@users.noreply.github.com
Requires-Python: >=3.7,<4.0
Classifier: Programming Language :: Python :: 3
Classifier: Programming Language :: Python :: 3.7
Classifier: Programming Language :: Python :: 3.8
Requires-Dist: biopython (>=1.76)
Requires-Dist: gensim (>=3.8.0)
Requires-Dist: mkkm_mr (>=0.2.1,<0.3.0)
Requires-Dist: mosek (>=9.2.0)
Requires-Dist: networkx (>=2.4.0)
Requires-Dist: numpy (>=1.18.0)
Requires-Dist: pandas (>=1.0.0)
Requires-Dist: requests (>=2.23.0)
Requires-Dist: scikit-learn (>=0.23.0)
Requires-Dist: scipy (>=1.5.2,<2.0.0)
Requires-Dist: snf_simple (>=0.1.0,<0.2.0)
Requires-Dist: snfpy
Project-URL: Repository, https://github.com/tastanlab/pamogk
